chronological/__init__.py
chronological-0.1.1.dist-info/LICENSE
chronological-0.1.1.dist-info/METADATA
chronological-0.1.1.dist-info/WHEEL
chronological-0.1.1.dist-info/top_level.txt
chronological-0.1.1.dist-info/RECORD
