Metadata-Version: 2.1
Name: chronological
Version: 0.1.1
Summary: Chain GPT calls like a pro!
Home-page: https://github.com/OthersideAI/chronology
Author: Otherside AI
Author-email: bram@othersideai.com
License: unlicense
Platform: UNKNOWN
Classifier: Programming Language :: Python :: 3
Classifier: License :: OSI Approved :: MIT License
Classifier: Operating System :: OS Independent
Requires-Python: >=3.7
